testwizard/core/CustomProperties.py
testwizard/core/EnvironmentInfo.py
testwizard/core/Errors.py
testwizard/core/ManagerSessionInfo.py
testwizard/core/Parameters.py
testwizard/core/RestClient.py
testwizard/core/ResultCodes.py
testwizard/core/RobotClient.py
testwizard/core/Session.py
testwizard/core/SessionInfo.py
testwizard/core/SideCarFileReader.py
testwizard/core/TestWizard.py
testwizard/core/__init__.py
testwizard/core/commands/AddCustomDataCommand.py
testwizard/core/commands/AddPerformanceDataCommand.py
testwizard/core/commands/BeginStepCommand.py
testwizard/core/commands/CancelCommandsCommand.py
testwizard/core/commands/EndStepCommand.py
testwizard/core/commands/EndStepResult.py
testwizard/core/commands/StepExecutionResult.py
testwizard/core/commands/StringCompareCommand.py
testwizard/core/commands/StringCompareResult.py
testwizard/core/commands/WaitForCommandCompletionCommand.py
testwizard/core/commands/__init__.py
testwizard/core/models/CreateTestRunRequest.py
testwizard/core/models/TestResult.py
testwizard/core/models/__init__.py
testwizard.core-3.8.1.dist-info/LICENSE.txt
testwizard.core-3.8.1.dist-info/METADATA
testwizard.core-3.8.1.dist-info/WHEEL
testwizard.core-3.8.1.dist-info/top_level.txt
testwizard.core-3.8.1.dist-info/RECORD
